vnpy_okx/__init__.py
vnpy_okx/okx_gateway.py
vnpy_okx/py.typed
vnpy_okx-2026.2.1.dist-info/METADATA
vnpy_okx-2026.2.1.dist-info/WHEEL
vnpy_okx-2026.2.1.dist-info/licenses/LICENSE
vnpy_okx-2026.2.1.dist-info/RECORD
