Metadata-Version: 2.4
Name: vnpy_okx
Version: 2026.2.1
Summary: OKX trading gateway for VeighNa.
Project-URL: Homepage, https://www.github.com/veighna-global
Project-URL: Source, https://www.github.com/veighna-global
Author-email: VeighNa Global <veighna@hotmail.com>
License: MIT
License-File: LICENSE
Keywords: algotrading,btc,crypto,investment,okx,quant,quantitative,trading
Classifier: Development Status :: 5 - Production/Stable
Classifier: License :: OSI Approved :: MIT License
Classifier: Natural Language :: English
Classifier: Operating System :: MacOS
Classifier: Operating System :: Microsoft :: Windows
Classifier: Operating System :: POSIX :: Linux
Classifier: Programming Language :: Python :: 3
Classifier: Programming Language :: Python :: 3.10
Classifier: Programming Language :: Python :: 3.11
Classifier: Programming Language :: Python :: 3.12
Classifier: Programming Language :: Python :: 3.13
Classifier: Programming Language :: Python :: Implementation :: CPython
Classifier: Topic :: Office/Business :: Financial :: Investment
Requires-Python: >=3.10
Requires-Dist: vnpy-rest
Requires-Dist: vnpy-websocket
